{
  "id": "3976454",
  "name": "go-vue",
  "font_family": "iconfont",
  "css_prefix_text": "icon-",
  "description": "",
  "glyphs": [
    {
      "icon_id": "577365",
      "name": "搜索",
      "font_class": "sousuo",
      "unicode": "e752",
      "unicode_decimal": 59218
    },
    {
      "icon_id": "715863",
      "name": "关闭",
      "font_class": "guanbi",
      "unicode": "e60b",
      "unicode_decimal": 58891
    },
    {
      "icon_id": "1975869",
      "name": "全屏",
      "font_class": "fangda",
      "unicode": "e66a",
      "unicode_decimal": 58986
    },
    {
      "icon_id": "2480673",
      "name": "修改密码",
      "font_class": "xiugaimima",
      "unicode": "e633",
      "unicode_decimal": 58931
    },
    {
      "icon_id": "6999203",
      "name": "缩小",
      "font_class": "suoxiao",
      "unicode": "e620",
      "unicode_decimal": 58912
    },
    {
      "icon_id": "11372694",
      "name": "设置",
      "font_class": "shezhi",
      "unicode": "e8b7",
      "unicode_decimal": 59575
    }
  ]
}
